rembg/__init__.py
rembg/_version.py
rembg/bg.py
rembg/session_base.py
rembg/session_factory.py
rembg/session_simple.py
rembg/u2net.onnx
rembg_aws_lambda-0.2.0.dist-info/LICENSE.txt
rembg_aws_lambda-0.2.0.dist-info/METADATA
rembg_aws_lambda-0.2.0.dist-info/WHEEL
rembg_aws_lambda-0.2.0.dist-info/top_level.txt
rembg_aws_lambda-0.2.0.dist-info/RECORD
